bkk.py
config.py
scheduleItem.py
bkk-1.0.2.dist-info/LICENSE
bkk-1.0.2.dist-info/METADATA
bkk-1.0.2.dist-info/WHEEL
bkk-1.0.2.dist-info/entry_points.txt
bkk-1.0.2.dist-info/top_level.txt
bkk-1.0.2.dist-info/RECORD
