Metadata-Version: 2.1
Name: bkk
Version: 1.0.2
Summary: Simple CLI app, displaying real-time data from BKK Futár API
Home-page: UNKNOWN
Author: Gergely Balint
License: UNKNOWN
Keywords: bkk futár cli
Platform: UNKNOWN
Requires-Python: >=3
Requires-Dist: Click
Requires-Dist: datetime
Requires-Dist: requests
